setup.py
teamspeak3/__init__.py
teamspeak3/client.py
teamspeak3/connection.py
teamspeak3/exceptions.py
teamspeak3/message.py
teamspeak3.egg-info/PKG-INFO
teamspeak3.egg-info/SOURCES.txt
teamspeak3.egg-info/dependency_links.txt
teamspeak3.egg-info/top_level.txt