Metadata-Version: 1.0
Name: teamspeak3
Version: 1.4.6
Summary: Interact with teamspeak clients from Python
Home-page: http://bitbucket.org/latestrevision/python-teamspeak3/
Author: Adam Coddington
Author-email: me@adamcoddington.net
License: UNKNOWN
Platform: UNKNOWN
Classifier: Intended Audience :: Developers
Classifier: License :: OSI Approved :: MIT License
Classifier: Operating System :: OS Independent
Classifier: Programming Language :: Python
Classifier: Topic :: Utilities
